{
	"Alley": { "value": "0c", "protection":0 },
	"Cardboard box": { "value": "100c", "protection":1 },
	"Cave": { "value": "1000c", "protection":2 },
	"Stable": { "value": "10000c", "protection":3 },
	"Shed": { "value": "1s", "protection":4 },
	"Shack": { "value": "10s", "protection":5 },
	"Barn": { "value": "100s", "protection":6 },
	"Hovel": { "value": "1000s", "protection":7 },
	"Cabin": { "value": "1g", "protection":8 },
	"Room above tavern": { "value": "10g", "protection":9 },
	"Townhouse": { "value": "100g", "protection":10 },
	"Manor house": { "value": "1000g", "protection":11 },
	"Monastery": { "value": "1p", "protection":12 },
	"Abbey": { "value": "10p", "protection":13 },
	"Castle": { "value": "100p", "protection":14 },
	"Cathedral": { "value": "500p", "protection":15 },
	"Stone Keep": { "value": "3000p", "protection":16 },
	"Royal Citadel": { "value": "12500p", "protection":17 },
	"Mountain": { "value": "50000p", "protection":18 }
}
